AUTHORS
LICENSE
MANIFEST.in
README.md
requirements.txt
setup.py
salesking/__init__.py
salesking/api.py
salesking/collection.py
salesking/exceptions.py
salesking/resources.py
salesking.egg-info/PKG-INFO
salesking.egg-info/SOURCES.txt
salesking.egg-info/dependency_links.txt
salesking.egg-info/not-zip-safe
salesking.egg-info/requires.txt
salesking.egg-info/top_level.txt
warlock/__init__.py
warlock/core.py
warlock/errors.py
warlock/model.py