Metadata-Version: 1.0
Name: salesking
Version: 0.0.1
Summary: SalesKing API Wrapper and SDK
Home-page: http://github.com/salesking/salesking_python_sdk
Author: Frank Bieniek
Author-email: fb@saleking.de
License: UNKNOWN
Platform: UNKNOWN
